{
  "MetaArgs": null,
  "Stages": [
    {
      "Name": "",
      "BaseName": "ubuntu",
      "SourceCode": "FROM ubuntu",
      "Platform": "",
      "From": {
        "Image": "ubuntu"
      },
      "Commands": [
        {
          "CmdLine": [
            "apt-get update"
          ],
          "Name": "run",
          "PrependShell": true
        },
        {
          "CmdLine": [
            "apt-get install -y python3"
          ],
          "Name": "run",
          "PrependShell": true
        },
        {
          "CmdLine": [
            "apt-get install -y npm"
          ],
          "Name": "run",
          "PrependShell": true
        },
        {
          "CmdLine": [
            "npm install http-server -g"
          ],
          "Name": "run",
          "PrependShell": true
        },
        {
          "Chown": "",
          "Name": "add",
          "SourcesAndDest": [
            "www/",
            "www/"
          ]
        },
        {
          "Name": "workdir",
          "Path": "www/"
        },
        {
          "CmdLine": [
            "http-server",
            "-p",
            "8000"
          ],
          "Name": "cmd",
          "PrependShell": false
        }
      ]
    }
  ]
}