{
  "MetaArgs": null,
  "Stages": [
    {
      "Name": "",
      "BaseName": "postgres:9.6.1",
      "SourceCode": "FROM postgres:9.6.1",
      "Platform": "",
      "From": {
        "Image": "postgres:9.6.1"
      },
      "Commands": [
        {
          "Maintainer": "Zhe Li (linuxcity.jn@gmail.com)",
          "Name": "maintainer"
        },
        {
          "Chown": "",
          "Name": "add",
          "SourcesAndDest": [
            "create_extension.sh",
            "docker-entrypoint-initdb.d/create_extension.sh"
          ]
        }
      ]
    }
  ]
}