{
  "MetaArgs": null,
  "Stages": [
    {
      "Name": "",
      "BaseName": "circleci/php:7.0-node-browsers",
      "SourceCode": "FROM circleci/php:7.0-node-browsers",
      "Platform": "",
      "From": {
        "Image": "circleci/php:7.0-node-browsers"
      },
      "Commands": [
        {
          "CmdLine": [
            "sudo apt-get update"
          ],
          "Name": "run",
          "PrependShell": true
        },
        {
          "CmdLine": [
            "sudo apt-get install -y libxml2-dev libbz2-dev libmcrypt-dev libzip-dev"
          ],
          "Name": "run",
          "PrependShell": true
        },
        {
          "CmdLine": [
            "sudo docker-php-ext-install soap"
          ],
          "Name": "run",
          "PrependShell": true
        },
        {
          "CmdLine": [
            "sudo docker-php-ext-install bz2"
          ],
          "Name": "run",
          "PrependShell": true
        },
        {
          "CmdLine": [
            "sudo docker-php-ext-install mcrypt"
          ],
          "Name": "run",
          "PrependShell": true
        },
        {
          "CmdLine": [
            "sudo docker-php-ext-install zip"
          ],
          "Name": "run",
          "PrependShell": true
        },
        {
          "CmdLine": [
            "sudo docker-php-ext-install intl"
          ],
          "Name": "run",
          "PrependShell": true
        },
        {
          "CmdLine": [
            "sudo docker-php-ext-install opcache"
          ],
          "Name": "run",
          "PrependShell": true
        },
        {
          "CmdLine": [
            "sudo rm -rf /usr/local/etc/php/conf.d/docker-php-ext-xdebug.ini"
          ],
          "Name": "run",
          "PrependShell": true
        },
        {
          "CmdLine": [
            "sudo npm install -g n"
          ],
          "Name": "run",
          "PrependShell": true
        },
        {
          "CmdLine": [
            "sudo n 6.9.5"
          ],
          "Name": "run",
          "PrependShell": true
        }
      ]
    }
  ]
}