{
  "MetaArgs": null,
  "Stages": [
    {
      "Name": "",
      "BaseName": "busybox",
      "SourceCode": "FROM busybox",
      "Platform": "",
      "From": {
        "Image": "busybox"
      },
      "Commands": [
        {
          "Maintainer": "cocuh \u003ccocuh.kk at gmail.com\u003e",
          "Name": "maintainer"
        },
        {
          "CmdLine": [
            "mkdir -p /var/www/years"
          ],
          "Name": "run",
          "PrependShell": true
        },
        {
          "Chown": "",
          "From": "",
          "Name": "copy",
          "SourcesAndDest": [
            "data",
            "/var/www/years"
          ]
        }
      ]
    }
  ]
}