{
  "MetaArgs": null,
  "Stages": [
    {
      "Name": "",
      "BaseName": "liulantao/fpm",
      "SourceCode": "FROM liulantao/fpm",
      "Platform": "",
      "From": {
        "Image": "liulantao/fpm"
      },
      "Commands": [
        {
          "Maintainer": "Liu Lantao \u003cliulantao@gmail.com\u003e",
          "Name": "maintainer"
        },
        {
          "Env": [
            {
              "Key": "REFRESHED_AT",
              "Value": "2015-12-03"
            }
          ],
          "Name": "env"
        },
        {
          "CmdLine": [
            "curl http://packages.erlang-solutions.com/rpm/centos/erlang_solutions.repo -o /etc/yum.repos.d/erlang_solutions.repo"
          ],
          "Name": "run",
          "PrependShell": true
        },
        {
          "CmdLine": [
            "yum install -yq erlang-18.0-1.el6.x86_64 git expat-devel redhat-lsb-core"
          ],
          "Name": "run",
          "PrependShell": true
        }
      ]
    }
  ]
}