{
  "MetaArgs": null,
  "Stages": [
    {
      "Name": "",
      "BaseName": "php:apache",
      "SourceCode": "FROM php:apache",
      "Platform": "",
      "From": {
        "Image": "php:apache"
      },
      "Commands": [
        {
          "Maintainer": "Movie Masher \u003csupport@moviemasher.com\u003e",
          "Name": "maintainer"
        },
        {
          "CmdLine": [
            "mkdir -p -m 0777 /tmp/moviemasher/log"
          ],
          "Name": "run",
          "PrependShell": true
        },
        {
          "CmdLine": [
            "mkdir -p -m 0777 /tmp/moviemasher/queue"
          ],
          "Name": "run",
          "PrependShell": true
        },
        {
          "CmdLine": [
            "mkdir -p -m 0777 /tmp/moviemasher/temporary"
          ],
          "Name": "run",
          "PrependShell": true
        },
        {
          "CmdLine": [
            "mkdir -p -m 0777 /var/www/html/user-media"
          ],
          "Name": "run",
          "PrependShell": true
        },
        {
          "CmdLine": [
            "mkdir -p -m 0777 /var/www/config"
          ],
          "Name": "run",
          "PrependShell": true
        },
        {
          "CmdLine": [
            "mkdir -p -m 0777 /var/www/user-data"
          ],
          "Name": "run",
          "PrependShell": true
        },
        {
          "Name": "volume",
          "Volumes": [
            "/tmp/moviemasher/log"
          ]
        },
        {
          "Name": "volume",
          "Volumes": [
            "/tmp/moviemasher/queue"
          ]
        },
        {
          "Name": "volume",
          "Volumes": [
            "/tmp/moviemasher/temporary"
          ]
        },
        {
          "Name": "volume",
          "Volumes": [
            "/var/www/html"
          ]
        },
        {
          "Chown": "",
          "From": "",
          "Name": "copy",
          "SourcesAndDest": [
            "config/docker/php.ini",
            "/usr/local/etc/php/conf.d/moviemasher.ini"
          ]
        },
        {
          "Chown": "",
          "From": "",
          "Name": "copy",
          "SourcesAndDest": [
            "config/docker/moviemasher.ini",
            "/var/www/config/moviemasher.ini"
          ]
        },
        {
          "Chown": "",
          "From": "",
          "Name": "copy",
          "SourcesAndDest": [
            "config/index.html",
            "/var/www/html/"
          ]
        },
        {
          "Chown": "",
          "From": "",
          "Name": "copy",
          "SourcesAndDest": [
            ".",
            "/var/www/html/angular-moviemasher/"
          ]
        }
      ]
    }
  ]
}