{
  "MetaArgs": null,
  "Stages": [
    {
      "Name": "",
      "BaseName": "area51/alpine",
      "SourceCode": "FROM area51/alpine",
      "Platform": "",
      "From": {
        "Image": "area51/alpine"
      },
      "Commands": [
        {
          "Maintainer": "Peter Mount \u003cpeter@retep.org\u003e",
          "Name": "maintainer"
        },
        {
          "Env": [
            {
              "Key": "JAVA_VERSION_MAJOR",
              "Value": "8"
            }
          ],
          "Name": "env"
        },
        {
          "Env": [
            {
              "Key": "JAVA_VERSION_MINOR",
              "Value": "131"
            }
          ],
          "Name": "env"
        },
        {
          "Env": [
            {
              "Key": "JAVA_VERSION_BUILD",
              "Value": "11"
            }
          ],
          "Name": "env"
        },
        {
          "Env": [
            {
              "Key": "JAVA_PACKAGE",
              "Value": "jre"
            }
          ],
          "Name": "env"
        },
        {
          "Env": [
            {
              "Key": "URL_ELEMENT",
              "Value": "d54c1d3a095b4ff2b6607d096fa80163"
            }
          ],
          "Name": "env"
        },
        {
          "Env": [
            {
              "Key": "PATH",
              "Value": "$PATH:/opt/jre/bin"
            }
          ],
          "Name": "env"
        },
        {
          "CmdLine": [
            "mkdir -p /opt \u0026\u0026    curl -jkLH \"Cookie: oraclelicense=accept-securebackup-cookie\" \t-o java.tar.gz\thttp://download.oracle.com/otn-pub/java/jdk/${JAVA_VERSION_MAJOR}u${JAVA_VERSION_MINOR}-b${JAVA_VERSION_BUILD}/${URL_ELEMENT}/${JAVA_PACKAGE}-${JAVA_VERSION_MAJOR}u${JAVA_VERSION_MINOR}-linux-x64.tar.gz \u0026\u0026    gunzip -c java.tar.gz | tar -xf - -C /opt \u0026\u0026 rm -f java.tar.gz \u0026\u0026    ln -s /opt/jre1.${JAVA_VERSION_MAJOR}.0_${JAVA_VERSION_MINOR} /opt/jre \u0026\u0026    rm -rf /opt/jre/lib/plugin.jar          /opt/jre/lib/ext/jfxrt.jar          /opt/jre/bin/javaws          /opt/jre/lib/javaws.jar          /opt/jre/lib/desktop          /opt/jre/plugin          /opt/jre/lib/deploy*          /opt/jre/lib/*javafx*          /opt/jre/lib/*jfx*          /opt/jre/lib/amd64/libdecora_sse.so          /opt/jre/lib/amd64/libprism_*.so          /opt/jre/lib/amd64/libfxplugins.so          /opt/jre/lib/amd64/libglass.so          /opt/jre/lib/amd64/libgstreamer-lite.so          /opt/jre/lib/amd64/libjavafx*.so          /opt/jre/lib/amd64/libjfx*.so \u0026\u0026    sed -e \"s|export PATH=|export PATH=/opt/jre/bin:|\" -i /etc/profile \u0026\u0026    curl -s https://letsencrypt.org/certs/lets-encrypt-x1-cross-signed.pem -o /lets-encrypt-x1-cross-signed.pem \u0026\u0026    curl -s https://letsencrypt.org/certs/lets-encrypt-x2-cross-signed.pem -o /lets-encrypt-x2-cross-signed.pem \u0026\u0026    curl -s https://letsencrypt.org/certs/lets-encrypt-x3-cross-signed.pem -o /lets-encrypt-x3-cross-signed.pem \u0026\u0026    curl -s https://letsencrypt.org/certs/lets-encrypt-x4-cross-signed.pem -o /lets-encrypt-x4-cross-signed.pem \u0026\u0026    /opt/jre/bin/keytool -trustcacerts -keystore /opt/jre/lib/security/cacerts -storepass changeit -noprompt -importcert -alias lets-encrypt-x1-cross-signed -file /lets-encrypt-x1-cross-signed.pem \u0026\u0026    /opt/jre/bin/keytool -trustcacerts -keystore /opt/jre/lib/security/cacerts -storepass changeit -noprompt -importcert -alias lets-encrypt-x2-cross-signed -file /lets-encrypt-x2-cross-signed.pem \u0026\u0026    /opt/jre/bin/keytool -trustcacerts -keystore /opt/jre/lib/security/cacerts -storepass changeit -noprompt -importcert -alias lets-encrypt-x3-cross-signed -file /lets-encrypt-x3-cross-signed.pem \u0026\u0026    /opt/jre/bin/keytool -trustcacerts -keystore /opt/jre/lib/security/cacerts -storepass changeit -noprompt -importcert -alias lets-encrypt-x4-cross-signed -file /lets-encrypt-x4-cross-signed.pem \u0026\u0026    rm -f /*.pem"
          ],
          "Name": "run",
          "PrependShell": true
        }
      ]
    }
  ]
}