{
  "MetaArgs": null,
  "Stages": [
    {
      "Name": "",
      "BaseName": "bradrydzewski/node:0.10",
      "SourceCode": "FROM bradrydzewski/node:0.10",
      "Platform": "",
      "From": {
        "Image": "bradrydzewski/node:0.10"
      },
      "Commands": [
        {
          "CmdLine": [
            "/home/ubuntu/nvm/v0.10.22/bin/npm install -g bower grunt-cli karma superstatic"
          ],
          "Name": "run",
          "PrependShell": true
        },
        {
          "CmdLine": [
            "sudo curl -sLo /usr/local/bin/ep https://github.com/kreuzwerker/envplate/releases/download/v0.0.5/ep-linux \u0026\u0026 sudo chmod +x /usr/local/bin/ep"
          ],
          "Name": "run",
          "PrependShell": true
        },
        {
          "Name": "workdir",
          "Path": "/app"
        },
        {
          "Name": "expose",
          "Ports": [
            "8080"
          ]
        },
        {
          "CmdLine": [
            "/usr/local/bin/ep",
            "/app/.env.json",
            "--",
            "/usr/local/bin/superstatic",
            "--port",
            "8080",
            "--host",
            "0.0.0.0",
            "--gzip"
          ],
          "Name": "cmd",
          "PrependShell": false
        }
      ]
    }
  ]
}