{
  "MetaArgs": null,
  "Stages": [
    {
      "Name": "",
      "BaseName": "node:alpine",
      "SourceCode": "FROM node:alpine",
      "Platform": "",
      "From": {
        "Image": "node:alpine"
      },
      "Commands": [
        {
          "CmdLine": [
            "npm install -g write-good  \u0026\u0026 echo \"I stole the cat.\" \u003e test.md  \u0026\u0026 write-good *.md  \u0026\u0026 rm test.md"
          ],
          "Name": "run",
          "PrependShell": true
        },
        {
          "Name": "workdir",
          "Path": "/app"
        },
        {
          "Name": "volume",
          "Volumes": [
            "/app"
          ]
        },
        {
          "CmdLine": [
            "write-good"
          ],
          "Name": "entrypoint",
          "PrependShell": false
        },
        {
          "CmdLine": [],
          "Name": "cmd",
          "PrependShell": false
        }
      ]
    }
  ]
}