{
  "MetaArgs": null,
  "Stages": [
    {
      "Name": "",
      "BaseName": "alpine:latest",
      "SourceCode": "FROM alpine:latest",
      "Platform": "",
      "From": {
        "Image": "alpine:latest"
      },
      "Commands": [
        {
          "CmdLine": [
            "set -x \t\u0026\u0026 sed -i 's/dl-cdn.alpinelinux.org/mirrors.ustc.edu.cn/g' /etc/apk/repositories \t\u0026\u0026 apk add --no-cache redis sed bash tzdata \t\u0026\u0026 cp /usr/share/zoneinfo/Asia/Shanghai /etc/localtime     \u0026\u0026 echo \"Asia/Shanghai\" \u003e /etc/timezone     \u0026\u0026 apk del --no-cache tzdata"
          ],
          "Name": "run",
          "PrependShell": true
        },
        {
          "Chown": "",
          "From": "",
          "Name": "copy",
          "SourcesAndDest": [
            "redis-master.conf",
            "/redis-master/redis.conf"
          ]
        },
        {
          "Chown": "",
          "From": "",
          "Name": "copy",
          "SourcesAndDest": [
            "redis-slave.conf",
            "/redis-slave/redis.conf"
          ]
        },
        {
          "Chown": "",
          "From": "",
          "Name": "copy",
          "SourcesAndDest": [
            "run.sh",
            "/run.sh"
          ]
        },
        {
          "CmdLine": [
            "chmod +x /run.sh"
          ],
          "Name": "run",
          "PrependShell": true
        },
        {
          "CmdLine": [
            "/run.sh"
          ],
          "Name": "cmd",
          "PrependShell": false
        },
        {
          "CmdLine": [
            "bash",
            "-c"
          ],
          "Name": "entrypoint",
          "PrependShell": false
        }
      ]
    }
  ]
}