{
  "MetaArgs": null,
  "Stages": [
    {
      "Name": "",
      "BaseName": "traefik",
      "SourceCode": "FROM traefik",
      "Platform": "",
      "From": {
        "Image": "traefik"
      },
      "Commands": [
        {
          "Chown": "",
          "Name": "add",
          "SourcesAndDest": [
            "traefik.toml",
            "."
          ]
        },
        {
          "Name": "expose",
          "Ports": [
            "80"
          ]
        },
        {
          "Name": "expose",
          "Ports": [
            "8080"
          ]
        },
        {
          "Name": "expose",
          "Ports": [
            "443"
          ]
        }
      ]
    }
  ]
}