{
  "MetaArgs": null,
  "Stages": [
    {
      "Name": "",
      "BaseName": "debian:jessie",
      "SourceCode": "FROM debian:jessie",
      "Platform": "",
      "From": {
        "Image": "debian:jessie"
      },
      "Commands": [
        {
          "Maintainer": "Christoph Döberl, christoph@doeberl.at",
          "Name": "maintainer"
        },
        {
          "CmdLine": [
            "apt-key adv --keyserver pool.sks-keyservers.net                 --recv-keys 11E9DE8848F2B65222AA75B8D1820DB22A11534E"
          ],
          "Name": "run",
          "PrependShell": true
        },
        {
          "CmdLine": [
            "bash -c \"echo 'deb http://weechat.org/debian jessie main' \u003e/etc/apt/sources.list.d/weechat.list\""
          ],
          "Name": "run",
          "PrependShell": true
        },
        {
          "CmdLine": [
            "apt-get update \u0026\u0026     apt-get upgrade -y"
          ],
          "Name": "run",
          "PrependShell": true
        },
        {
          "Env": [
            {
              "Key": "TERM",
              "Value": "rxvt-unicode-256color"
            }
          ],
          "Name": "env"
        },
        {
          "CmdLine": [
            "echo \"Europe/Berlin\" | tee /etc/timezone"
          ],
          "Name": "run",
          "PrependShell": true
        },
        {
          "CmdLine": [
            "dpkg-reconfigure --frontend noninteractive tzdata"
          ],
          "Name": "run",
          "PrependShell": true
        },
        {
          "CmdLine": [
            "apt-get -y install     locales     python-potr     rxvt-unicode-256color     weechat     weechat-scripts"
          ],
          "Name": "run",
          "PrependShell": true
        },
        {
          "CmdLine": [
            "echo \"en_US.UTF-8 UTF-8\" \u003e /etc/locale.gen"
          ],
          "Name": "run",
          "PrependShell": true
        },
        {
          "CmdLine": [
            "locale-gen"
          ],
          "Name": "run",
          "PrependShell": true
        },
        {
          "Env": [
            {
              "Key": "LANG",
              "Value": "en_US.UTF-8"
            }
          ],
          "Name": "env"
        },
        {
          "Env": [
            {
              "Key": "LANGUAGE",
              "Value": "en_US.UTF-8"
            }
          ],
          "Name": "env"
        },
        {
          "Env": [
            {
              "Key": "LC_ALL",
              "Value": "en_US.UTF-8"
            }
          ],
          "Name": "env"
        },
        {
          "CmdLine": [
            "adduser --disabled-login --gecos '' user"
          ],
          "Name": "run",
          "PrependShell": true
        },
        {
          "Name": "user",
          "User": "user"
        },
        {
          "Name": "workdir",
          "Path": "/home/user"
        },
        {
          "CmdLine": [
            "weechat"
          ],
          "Name": "entrypoint",
          "PrependShell": true
        }
      ]
    }
  ]
}