{
  "MetaArgs": null,
  "Stages": [
    {
      "Name": "",
      "BaseName": "ubuntu:16.04",
      "SourceCode": "FROM ubuntu:16.04",
      "Platform": "",
      "From": {
        "Image": "ubuntu:16.04"
      },
      "Commands": [
        {
          "Maintainer": "Jean-Daniel Gasser \u003cjean-daniel.gasser@altran.com\u003e",
          "Name": "maintainer"
        },
        {
          "CmdLine": [
            "apt-get update -y"
          ],
          "Name": "run",
          "PrependShell": true
        },
        {
          "CmdLine": [
            "apt-get install -y apache2 vim bash-completion unzip"
          ],
          "Name": "run",
          "PrependShell": true
        },
        {
          "CmdLine": [
            "mkdir -p /var/lock/apache2 /var/run/apache2"
          ],
          "Name": "run",
          "PrependShell": true
        },
        {
          "CmdLine": [
            "DEBIAN_FRONTEND=noninteractive apt-get install -y mysql-client mysql-server"
          ],
          "Name": "run",
          "PrependShell": true
        },
        {
          "CmdLine": [
            "mkdir -p /data/db"
          ],
          "Name": "run",
          "PrependShell": true
        },
        {
          "CmdLine": [
            "apt-get install -y mongodb mongodb-server mongodb-clients"
          ],
          "Name": "run",
          "PrependShell": true
        },
        {
          "CmdLine": [
            "apt-get install -y php7.0 php7.0-mysql libapache2-mod-php7.0"
          ],
          "Name": "run",
          "PrependShell": true
        },
        {
          "CmdLine": [
            "apt-get install -y curl"
          ],
          "Name": "run",
          "PrependShell": true
        },
        {
          "CmdLine": [
            "apt-get install -y sudo"
          ],
          "Name": "run",
          "PrependShell": true
        },
        {
          "CmdLine": [
            "apt-get install -y net-tools"
          ],
          "Name": "run",
          "PrependShell": true
        },
        {
          "CmdLine": [
            "curl -sL https://deb.nodesource.com/setup_8.x | sudo bash -"
          ],
          "Name": "run",
          "PrependShell": true
        },
        {
          "CmdLine": [
            "apt-get install -y nodejs"
          ],
          "Name": "run",
          "PrependShell": true
        },
        {
          "CmdLine": [
            "apt-get install -y git"
          ],
          "Name": "run",
          "PrependShell": true
        },
        {
          "CmdLine": [
            "apt-get install -y openssh-server openssh-client passwd"
          ],
          "Name": "run",
          "PrependShell": true
        },
        {
          "CmdLine": [
            "mkdir -p /var/run/sshd"
          ],
          "Name": "run",
          "PrependShell": true
        },
        {
          "CmdLine": [
            "sed -ri 's/^PermitRootLogin\\s+.*/PermitRootLogin yes/' /etc/ssh/sshd_config"
          ],
          "Name": "run",
          "PrependShell": true
        },
        {
          "CmdLine": [
            "sed -ri 's/UsePAM yes/#UsePAM yes/g' /etc/ssh/sshd_config"
          ],
          "Name": "run",
          "PrependShell": true
        },
        {
          "CmdLine": [
            "echo 'root:root' | chpasswd"
          ],
          "Name": "run",
          "PrependShell": true
        },
        {
          "CmdLine": [
            "mkdir -p /root/.ssh \u0026\u0026 touch /root/.ssh/known_hosts \u0026\u0026 chmod 700 /root/.ssh"
          ],
          "Name": "run",
          "PrependShell": true
        },
        {
          "Chown": "",
          "Name": "add",
          "SourcesAndDest": [
            "known_hosts",
            "/root/.ssh/known_hosts"
          ]
        },
        {
          "CmdLine": [
            "apt-get install -y python-setuptools"
          ],
          "Name": "run",
          "PrependShell": true
        },
        {
          "Chown": "",
          "Name": "add",
          "SourcesAndDest": [
            "rancher/",
            "/rancher-gitlab-deploy"
          ]
        },
        {
          "Name": "workdir",
          "Path": "/rancher-gitlab-deploy"
        },
        {
          "CmdLine": [
            "python /rancher-gitlab-deploy/setup.py install"
          ],
          "Name": "run",
          "PrependShell": true
        },
        {
          "CmdLine": [
            "ln -s /usr/local/bin/rancher-gitlab-deploy /usr/local/bin/upgrade"
          ],
          "Name": "run",
          "PrependShell": true
        },
        {
          "CmdLine": [
            "apt-get install -y dbconfig-common dbconfig-mysql fontconfig-config fonts-dejavu-core javascript-common libfontconfig1 libfreetype6 libgd3 libjbig0 libjpeg-turbo8 libjpeg8 libjs-jquery libjs-sphinxdoc libjs-underscore libmcrypt4 libpng12-0 libtiff5 libvpx3 libxpm4 libxslt1.1 php-gd php-gettext php-mbstring php-mcrypt php-pear php-phpseclib php-tcpdf php-xml php7.0-gd php7.0-mbstring php7.0-mcrypt php7.0-xml"
          ],
          "Name": "run",
          "PrependShell": true
        },
        {
          "Chown": "",
          "Name": "add",
          "SourcesAndDest": [
            "script.sh",
            "/root/"
          ]
        },
        {
          "Chown": "",
          "Name": "add",
          "SourcesAndDest": [
            "key_rsa",
            "/root/"
          ]
        },
        {
          "Chown": "",
          "Name": "add",
          "SourcesAndDest": [
            "version.txt",
            "/root/"
          ]
        },
        {
          "Chown": "",
          "Name": "add",
          "SourcesAndDest": [
            "vhost_backend.conf",
            "/etc/apache2/sites-available/"
          ]
        },
        {
          "Chown": "",
          "Name": "add",
          "SourcesAndDest": [
            ".bashrc",
            "/root/"
          ]
        },
        {
          "Name": "expose",
          "Ports": [
            "22",
            "3306",
            "80",
            "8080"
          ]
        },
        {
          "CmdLine": [
            "service mysql start \u0026\u0026 service apache2 start \u0026\u0026 service mongodb start \u0026\u0026 /usr/sbin/sshd -D"
          ],
          "Name": "cmd",
          "PrependShell": true
        }
      ]
    }
  ]
}