{
  "MetaArgs": null,
  "Stages": [
    {
      "Name": "",
      "BaseName": "java:8-jre",
      "SourceCode": "FROM java:8-jre",
      "Platform": "",
      "From": {
        "Image": "java:8-jre"
      },
      "Commands": [
        {
          "Env": [
            {
              "Key": "JAVA_HOME",
              "Value": "/usr/lib/jvm/java-8-openjdk-amd64/jre"
            }
          ],
          "Name": "env"
        },
        {
          "Env": [
            {
              "Key": "GRAYLOG_SERVER_JAVA_OPTS",
              "Value": "\"-Xms1g -Xmx2g -XX:NewRatio=1 -XX:MaxMetaspaceSize=256m -server -XX:+ResizeTLAB -XX:+UseConcMarkSweepGC -XX:+CMSConcurrentMTEnabled -XX:+CMSClassUnloadingEnabled -XX:+UseParNewGC -XX:-OmitStackTraceInFastThrow\""
            }
          ],
          "Name": "env"
        },
        {
          "Env": [
            {
              "Key": "GOSU_VERSION",
              "Value": "1.7"
            }
          ],
          "Name": "env"
        },
        {
          "CmdLine": [
            "set -x   \u0026\u0026 wget -O /usr/local/bin/gosu \"https://github.com/tianon/gosu/releases/download/$GOSU_VERSION/gosu-$(dpkg --print-architecture)\"   \u0026\u0026 wget -O /usr/local/bin/gosu.asc \"https://github.com/tianon/gosu/releases/download/$GOSU_VERSION/gosu-$(dpkg --print-architecture).asc\"   \u0026\u0026 export GNUPGHOME=\"$(mktemp -d)\"   \u0026\u0026 gpg --keyserver ha.pool.sks-keyservers.net --recv-keys B42F6819007F00F88E364FD4036A9C25BF357DD4   \u0026\u0026 gpg --batch --verify /usr/local/bin/gosu.asc /usr/local/bin/gosu   \u0026\u0026 rm -r \"$GNUPGHOME\" /usr/local/bin/gosu.asc   \u0026\u0026 chmod +x /usr/local/bin/gosu   \u0026\u0026 gosu nobody true"
          ],
          "Name": "run",
          "PrependShell": true
        },
        {
          "CmdLine": [
            "apt-get update   \u0026\u0026 apt-get install -y apt-transport-https   \u0026\u0026 wget https://packages.graylog2.org/repo/packages/graylog-2.1-repository_latest.deb   \u0026\u0026 dpkg -i graylog-2.1-repository_latest.deb   \u0026\u0026 apt-get update   \u0026\u0026 apt-get install -y graylog-server   \u0026\u0026 apt-get clean   \u0026\u0026 rm -rf /var/lib/apt/lists/*"
          ],
          "Name": "run",
          "PrependShell": true
        },
        {
          "CmdLine": [
            "apt-key adv --keyserver ha.pool.sks-keyservers.net --recv-keys 46095ACC8548582C1A2699A9D27D666CD88E42B4"
          ],
          "Name": "run",
          "PrependShell": true
        },
        {
          "Env": [
            {
              "Key": "ELASTICSEARCH_VERSION",
              "Value": "2.4.0"
            }
          ],
          "Name": "env"
        },
        {
          "Env": [
            {
              "Key": "ELASTICSEARCH_REPO_BASE",
              "Value": "http://packages.elasticsearch.org/elasticsearch/2.x/debian"
            }
          ],
          "Name": "env"
        },
        {
          "CmdLine": [
            "echo \"deb $ELASTICSEARCH_REPO_BASE stable main\" \u003e /etc/apt/sources.list.d/elasticsearch.list"
          ],
          "Name": "run",
          "PrependShell": true
        },
        {
          "CmdLine": [
            "set -x \t\u0026\u0026 apt-get update \t\u0026\u0026 apt-get install -y --no-install-recommends elasticsearch=$ELASTICSEARCH_VERSION \t\u0026\u0026 rm -rf /var/lib/apt/lists/*"
          ],
          "Name": "run",
          "PrependShell": true
        },
        {
          "CmdLine": [
            "set -x \t\u0026\u0026 apt-get update \t\u0026\u0026 apt-get install -y python-setuptools \t\u0026\u0026 rm -rf /var/lib/apt/lists/*"
          ],
          "Name": "run",
          "PrependShell": true
        },
        {
          "CmdLine": [
            "easy_install supervisor"
          ],
          "Name": "run",
          "PrependShell": true
        },
        {
          "Env": [
            {
              "Key": "PATH",
              "Value": "/usr/share/graylog-server/bin:/usr/share/elasticsearch/bin:$PATH"
            }
          ],
          "Name": "env"
        },
        {
          "Name": "workdir",
          "Path": "/usr/share/elasticsearch"
        },
        {
          "CmdLine": [
            "set -ex \t\u0026\u0026 for path in \t\t./data \t\t./logs \t\t./config \t\t./config/scripts \t; do \t\tmkdir -p \"$path\"; \t\tchown -R elasticsearch:elasticsearch \"$path\"; \tdone"
          ],
          "Name": "run",
          "PrependShell": true
        },
        {
          "Chown": "",
          "From": "",
          "Name": "copy",
          "SourcesAndDest": [
            "config_es",
            "./config"
          ]
        },
        {
          "Name": "workdir",
          "Path": "/usr/share/graylog-server"
        },
        {
          "CmdLine": [
            "set -ex   \u0026\u0026 for path in     ./data/journal     ./data/log     ./data/config   ; do     mkdir -p \"$path\";   done"
          ],
          "Name": "run",
          "PrependShell": true
        },
        {
          "Chown": "",
          "From": "",
          "Name": "copy",
          "SourcesAndDest": [
            "config_graylog",
            "./data/config"
          ]
        },
        {
          "Chown": "",
          "From": "",
          "Name": "copy",
          "SourcesAndDest": [
            "supervisord.conf",
            "/etc/supervisord.conf"
          ]
        },
        {
          "Chown": "",
          "From": "",
          "Name": "copy",
          "SourcesAndDest": [
            "docker-entrypoint.sh",
            "/"
          ]
        },
        {
          "CmdLine": [
            "chmod u+x /docker-entrypoint.sh"
          ],
          "Name": "run",
          "PrependShell": true
        },
        {
          "Name": "volume",
          "Volumes": [
            "/usr/share/elasticsearch/data"
          ]
        },
        {
          "Name": "expose",
          "Ports": [
            "12900",
            "9000"
          ]
        },
        {
          "CmdLine": [
            "/docker-entrypoint.sh"
          ],
          "Name": "entrypoint",
          "PrependShell": false
        },
        {
          "CmdLine": [
            "start"
          ],
          "Name": "cmd",
          "PrependShell": false
        }
      ]
    }
  ]
}