{
  "MetaArgs": null,
  "Stages": [
    {
      "Name": "",
      "BaseName": "gcr.io/google_containers/etcd:3.2.24",
      "SourceCode": "FROM gcr.io/google_containers/etcd:3.2.24",
      "Platform": "",
      "From": {
        "Image": "gcr.io/google_containers/etcd:3.2.24"
      },
      "Commands": [
        {
          "Maintainer": "yujia \u003cyu-jiac@dxc.com\u003e",
          "Name": "maintainer"
        },
        {
          "Labels": [
            {
              "Key": "name",
              "Value": "\"etcd\""
            },
            {
              "Key": "license",
              "Value": "\"GPLv2\""
            },
            {
              "Key": "build-date",
              "Value": "\"20190117\""
            }
          ],
          "Name": "label"
        }
      ]
    }
  ]
}