{
  "MetaArgs": null,
  "Stages": [
    {
      "Name": "",
      "BaseName": "evarga/jenkins-slave",
      "SourceCode": "FROM evarga/jenkins-slave",
      "Platform": "",
      "From": {
        "Image": "evarga/jenkins-slave"
      },
      "Commands": [
        {
          "Maintainer": "filip@devzion.xyz",
          "Name": "maintainer"
        },
        {
          "CmdLine": [
            "apt-get update"
          ],
          "Name": "run",
          "PrependShell": true
        },
        {
          "CmdLine": [
            "apt-get install -y git jq wget xz-utils build-essential python maven"
          ],
          "Name": "run",
          "PrependShell": true
        },
        {
          "CmdLine": [
            "wget https://nodejs.org/dist/v4.4.4/node-v4.4.4-linux-x64.tar.xz -P /tmp"
          ],
          "Name": "run",
          "PrependShell": true
        },
        {
          "CmdLine": [
            "tar -C /usr/local --strip-components 1 -xJf /tmp/node-v4.4.4-linux-x64.tar.xz"
          ],
          "Name": "run",
          "PrependShell": true
        },
        {
          "CmdLine": [
            "npm install -g npm@3"
          ],
          "Name": "run",
          "PrependShell": true
        }
      ]
    }
  ]
}