{
  "MetaArgs": null,
  "Stages": [
    {
      "Name": "",
      "BaseName": "redis:4.0.6-alpine",
      "SourceCode": "FROM redis:4.0.6-alpine",
      "Platform": "",
      "From": {
        "Image": "redis:4.0.6-alpine"
      },
      "Commands": [
        {
          "Maintainer": "Weithenn Wang \u003cweithenn@weithenn.org\u003e",
          "Name": "maintainer"
        },
        {
          "CmdLine": [
            "apk add --no-cache tzdata \u0026\u0026         cd /tmp \u0026\u0026     wget http://download.redis.io/redis-stable/sentinel.conf \u0026\u0026     mkdir -p /etc/redis \u0026\u0026     cp sentinel.conf /etc/redis/ \u0026\u0026     sed -i 's,# protected-mode no,protected-mode no,g' /etc/redis/sentinel.conf \u0026\u0026     sed -i 's,sentinel monitor mymaster 127.0.0.1 6379 2,sentinel monitor redis-ha redis_master 6379 2,g' /etc/redis/sentinel.conf \u0026\u0026     sed -i 's,sentinel down-after-milliseconds mymaster 30000,sentinel down-after-milliseconds redis-ha 5000,g' /etc/redis/sentinel.conf \u0026\u0026     sed -i 's,sentinel parallel-syncs mymaster 1,sentinel parallel-syncs redis-ha 1,g' /etc/redis/sentinel.conf \u0026\u0026     sed -i 's,sentinel failover-timeout mymaster 180000,sentinel failover-timeout redis-ha 60000,g' /etc/redis/sentinel.conf \u0026\u0026         touch /etc/redis/run.sh \u0026\u0026     echo \"echo 32768 \u003e /wproc/sys/net/core/somaxconn\" \u003e\u003e /etc/redis/run.sh \u0026\u0026     echo \"redis-sentinel /etc/redis/sentinel.conf\" \u003e\u003e /etc/redis/run.sh \u0026\u0026     chmod 755 /etc/redis/run.sh \u0026\u0026     chown -R redis:redis /etc/redis"
          ],
          "Name": "run",
          "PrependShell": true
        },
        {
          "Env": [
            {
              "Key": "TZ",
              "Value": "Asia/Taipei"
            }
          ],
          "Name": "env"
        },
        {
          "Name": "expose",
          "Ports": [
            "26379/tcp"
          ]
        },
        {
          "CmdLine": [
            "/etc/redis/run.sh"
          ],
          "Name": "cmd",
          "PrependShell": false
        }
      ]
    }
  ]
}