{
  "MetaArgs": null,
  "Stages": [
    {
      "Name": "",
      "BaseName": "blacklabelops/volumerize",
      "SourceCode": "FROM blacklabelops/volumerize",
      "Platform": "",
      "From": {
        "Image": "blacklabelops/volumerize"
      },
      "Commands": [
        {
          "CmdLine": [
            "apk add --no-cache     mongodb-tools"
          ],
          "Name": "run",
          "PrependShell": true
        },
        {
          "Chown": "",
          "From": "",
          "Name": "copy",
          "SourcesAndDest": [
            "postexecute",
            "/postexecute"
          ]
        },
        {
          "Chown": "",
          "From": "",
          "Name": "copy",
          "SourcesAndDest": [
            "preexecute",
            "/preexecute"
          ]
        }
      ]
    }
  ]
}