{
  "MetaArgs": null,
  "Stages": [
    {
      "Name": "",
      "BaseName": "ubuntu:16.04",
      "SourceCode": "FROM ubuntu:16.04",
      "Platform": "",
      "From": {
        "Image": "ubuntu:16.04"
      },
      "Commands": [
        {
          "Env": [
            {
              "Key": "DEBIAN_FRONTEND",
              "Value": "noninteractive"
            }
          ],
          "Name": "env"
        },
        {
          "CmdLine": [
            "apt-get --quiet --yes update \u0026\u0026     apt-get --quiet --yes install wget build-essential git bc device-tree-compiler libncurses-dev python libfdt-dev"
          ],
          "Name": "run",
          "PrependShell": true
        },
        {
          "CmdLine": [
            "mkdir -p /opt/linaro/aarch64 \u0026\u0026 cd /opt/linaro/aarch64 \u0026\u0026 wget --quiet --output-document linaro-cross.tar.xz https://releases.linaro.org/14.11/components/toolchain/binaries/aarch64-linux-gnu/gcc-linaro-4.9-2014.11-x86_64_aarch64-linux-gnu.tar.xz \u0026\u0026 tar xf linaro-cross.tar.xz --strip-components=1 \u0026\u0026 rm linaro-cross.tar.xz"
          ],
          "Name": "run",
          "PrependShell": true
        },
        {
          "CmdLine": [
            "mkdir -p /opt/codeaurora/ \u0026\u0026 cd /opt/codeaurora/ \u0026\u0026 git clone git://codeaurora.org/quic/kernel/skales"
          ],
          "Name": "run",
          "PrependShell": true
        },
        {
          "CmdLine": [
            "mkdir -p /opt/codeaurora/ \u0026\u0026 cd /opt/codeaurora/ \u0026\u0026 git clone git://codeaurora.org/platform/prebuilts/gcc/linux-x86/arm/arm-eabi-4.8.git -b LA.BR.1.1.3.c4-01000-8x16.0"
          ],
          "Name": "run",
          "PrependShell": true
        },
        {
          "CmdLine": [
            "apt-get clean \u0026\u0026 \trm -rf /var/lib/apt/lists/* /tmp/* /var/tmp/*"
          ],
          "Name": "run",
          "PrependShell": true
        },
        {
          "CmdLine": [
            "mkdir /source"
          ],
          "Name": "run",
          "PrependShell": true
        },
        {
          "Env": [
            {
              "Key": "PATH",
              "Value": "/opt/linaro/aarch64/bin:/opt/codeaurora/skales:/opt/codeaurora/arm-eabi-4.8/bin:$PATH"
            }
          ],
          "Name": "env"
        },
        {
          "Env": [
            {
              "Key": "CROSS_COMPILE",
              "Value": "aarch64-linux-gnu-"
            }
          ],
          "Name": "env"
        },
        {
          "Name": "volume",
          "Volumes": [
            "/source"
          ]
        },
        {
          "Name": "workdir",
          "Path": "/source"
        },
        {
          "CmdLine": [
            "/bin/bash"
          ],
          "Name": "cmd",
          "PrependShell": false
        }
      ]
    }
  ]
}