{
  "MetaArgs": null,
  "Stages": [
    {
      "Name": "",
      "BaseName": "pytorch/pytorch:1.0-cuda10.0-cudnn7-runtime",
      "SourceCode": "FROM pytorch/pytorch:1.0-cuda10.0-cudnn7-runtime",
      "Platform": "",
      "From": {
        "Image": "pytorch/pytorch:1.0-cuda10.0-cudnn7-runtime"
      },
      "Commands": [
        {
          "Maintainer": "Fatih Baltacı \"baltacifatih14@gmail.com\"",
          "Name": "maintainer"
        },
        {
          "CmdLine": [
            "apt-get update \u0026\u0026 apt-get install -y wget vim unzip libgtk2.0-dev swig"
          ],
          "Name": "run",
          "PrependShell": true
        },
        {
          "CmdLine": [
            "pip --no-cache-dir install \topencv-contrib-python==4.1.0.25 \tmlflow==0.9.1 \tyoutube-dl \tscikit-image==0.13.1 \tmatplotlib==3.1.0 \tPillow==5.3.0 \tCython==0.29.9 \twget==3.2 \tfuture==0.17.1 \tjupyterlab==1.0.5"
          ],
          "Name": "run",
          "PrependShell": true
        },
        {
          "Chown": "",
          "From": "",
          "Name": "copy",
          "SourcesAndDest": [
            "jupyter_notebook_config.py",
            "/root/.jupyter/jupyter_notebook_config.py"
          ]
        },
        {
          "Env": [
            {
              "Key": "PASSWORD",
              "Value": "\"Jupyter\""
            }
          ],
          "Name": "env"
        },
        {
          "Env": [
            {
              "Key": "LC_ALL",
              "Value": "C.UTF-8"
            }
          ],
          "Name": "env"
        },
        {
          "Env": [
            {
              "Key": "LANG",
              "Value": "C.UTF-8"
            }
          ],
          "Name": "env"
        },
        {
          "CmdLine": [
            "ln -sf /usr/share/zoneinfo/Turkey /etc/localtime"
          ],
          "Name": "run",
          "PrependShell": true
        },
        {
          "Name": "workdir",
          "Path": "/workspace"
        },
        {
          "CmdLine": [
            "jupyter",
            "lab"
          ],
          "Name": "cmd",
          "PrependShell": false
        }
      ]
    }
  ]
}