{
  "MetaArgs": null,
  "Stages": [
    {
      "Name": "",
      "BaseName": "ubuntu:utopic",
      "SourceCode": "FROM ubuntu:utopic",
      "Platform": "",
      "From": {
        "Image": "ubuntu:utopic"
      },
      "Commands": [
        {
          "Maintainer": "Jonathan Raffre \u003cnk@nyuu.eu\u003e",
          "Name": "maintainer"
        },
        {
          "CmdLine": [
            "apt-get update \u0026\u0026 apt-get install -y --no-install-recommends     software-properties-common     bzr     git     mercurial     openssh-client     subversion     \u0026\u0026 rm -rf /var/lib/apt/lists/*"
          ],
          "Name": "run",
          "PrependShell": true
        }
      ]
    }
  ]
}