{
  "MetaArgs": null,
  "Stages": [
    {
      "Name": "",
      "BaseName": "ubuntu:14.04",
      "SourceCode": "FROM ubuntu:14.04",
      "Platform": "",
      "From": {
        "Image": "ubuntu:14.04"
      },
      "Commands": [
        {
          "CmdLine": [
            "echo version 20151228"
          ],
          "Name": "run",
          "PrependShell": true
        },
        {
          "CmdLine": [
            "apt-get update \u0026\u0026 apt-get upgrade -y \u0026\u0026 apt-get install -y   apache2-utils   command-not-found   curl   dnsutils   git   htop   libmysqlclient-dev mysql-client   man-db   nodejs   openssh-client   openssh-server   redis-tools   screen tmux   silversearcher-ag   telnet   traceroute nethogs   vim emacs nano ne"
          ],
          "Name": "run",
          "PrependShell": true
        }
      ]
    }
  ]
}