{
  "MetaArgs": null,
  "Stages": [
    {
      "Name": "",
      "BaseName": "sangwo/archlinux:latest",
      "SourceCode": "FROM sangwo/archlinux:latest",
      "Platform": "",
      "From": {
        "Image": "sangwo/archlinux:latest"
      },
      "Commands": [
        {
          "Env": [
            {
              "Key": "MY_USERNAME",
              "Value": "haoliang"
            }
          ],
          "Name": "env"
        },
        {
          "Chown": "",
          "From": "",
          "Name": "copy",
          "SourcesAndDest": [
            "./docker/scripts/",
            "/usr/local/bin"
          ]
        },
        {
          "CmdLine": [
            "pacman -Sy --noconfirm \u0026\u0026 pacman -S --noconfirm --needed     php     xdebug     php-intl     php-mongodb     composer"
          ],
          "Name": "run",
          "PrependShell": true
        },
        {
          "Name": "user",
          "User": "$MY_USERNAME"
        },
        {
          "CmdLine": [
            "cower_install.sh php-swoole"
          ],
          "Name": "run",
          "PrependShell": true
        },
        {
          "Name": "user",
          "User": "root"
        },
        {
          "Chown": "",
          "From": "",
          "Name": "copy",
          "SourcesAndDest": [
            "./docker/config/php/php.ini",
            "/etc/php/php.ini"
          ]
        },
        {
          "Chown": "",
          "From": "",
          "Name": "copy",
          "SourcesAndDest": [
            "./docker/config/php/ext/",
            "/etc/php/conf.d/"
          ]
        },
        {
          "CmdLine": [
            "pacman -Sy --noconfirm \u0026\u0026 pacman -S --noconfirm --needed     go go-tools     delve dep"
          ],
          "Name": "run",
          "PrependShell": true
        },
        {
          "Name": "user",
          "User": "$MY_USERNAME"
        },
        {
          "CmdLine": [
            "cower_install.sh gometalinter-git"
          ],
          "Name": "run",
          "PrependShell": true
        },
        {
          "Name": "user",
          "User": "root"
        },
        {
          "CmdLine": [
            "pacman -Sy --noconfirm \u0026\u0026 pacman -S --noconfirm --needed     python python-docs     python-pip python-wheel     python-pylint flake8 mypy     ipython     poetry"
          ],
          "Name": "run",
          "PrependShell": true
        },
        {
          "CmdLine": [
            "pacman -Sy --noconfirm \u0026\u0026 pacman -S --noconfirm --needed     traceroute     bind-tools     tcpdump     sysstat     socat     strace     inotify-tools     netcat     openssh     openssl     lsof     whois     mosh     time     colordiff"
          ],
          "Name": "run",
          "PrependShell": true
        },
        {
          "CmdLine": [
            "pacman -Sy --noconfirm \u0026\u0026 pacman -S --noconfirm --needed     neovim python-neovim     zsh grml-zsh-config     tmux     the_silver_searcher     fzf     shellcheck ctags     jq     vifm     stow     z"
          ],
          "Name": "run",
          "PrependShell": true
        },
        {
          "CmdLine": [
            "pacman -Sy --noconfirm \u0026\u0026 pacman -S --noconfirm --needed     mariadb-clients     tree     bc     p7zip     dos2unix     proxychains-ng     ansible ansible-lint"
          ],
          "Name": "run",
          "PrependShell": true
        },
        {
          "Name": "user",
          "User": "$MY_USERNAME"
        },
        {
          "CmdLine": [
            "cower_install.sh gotty"
          ],
          "Name": "run",
          "PrependShell": true
        },
        {
          "CmdLine": [
            "cower_install.sh fpp-git"
          ],
          "Name": "run",
          "PrependShell": true
        },
        {
          "Name": "user",
          "User": "root"
        },
        {
          "CmdLine": [
            "pacman -Syu --noconfirm"
          ],
          "Name": "run",
          "PrependShell": true
        },
        {
          "CmdLine": [
            "pacman -Scc --noconfirm"
          ],
          "Name": "run",
          "PrependShell": true
        },
        {
          "CmdLine": [
            "rm -rf /tmp/*"
          ],
          "Name": "run",
          "PrependShell": true
        },
        {
          "Name": "volume",
          "Volumes": [
            "/srv/http"
          ]
        },
        {
          "Name": "volume",
          "Volumes": [
            "/root"
          ]
        },
        {
          "Name": "volume",
          "Volumes": [
            "/home/$MY_USERNAME"
          ]
        },
        {
          "Name": "volume",
          "Volumes": [
            "/srv/golang"
          ]
        },
        {
          "Name": "workdir",
          "Path": "/srv/http"
        },
        {
          "Name": "user",
          "User": "$MY_USERNAME"
        },
        {
          "CmdLine": [
            "docker_entrypoint"
          ],
          "Name": "entrypoint",
          "PrependShell": false
        }
      ]
    }
  ]
}