{
  "MetaArgs": null,
  "Stages": [
    {
      "Name": "",
      "BaseName": "ubuntu:18.04",
      "SourceCode": "FROM ubuntu:18.04",
      "Platform": "",
      "From": {
        "Image": "ubuntu:18.04"
      },
      "Commands": [
        {
          "CmdLine": [
            "apt-get update \u0026\u0026     apt-get install -y --no-install-recommends cron mysql-client python3-pip python3-setuptools python3-wheel \u0026\u0026     pip3 install awscli \u0026\u0026     mkdir /backup"
          ],
          "Name": "run",
          "PrependShell": true
        },
        {
          "Env": [
            {
              "Key": "CRON_TIME",
              "Value": "\"0 0 * * *\""
            }
          ],
          "Name": "env"
        },
        {
          "Chown": "",
          "Name": "add",
          "SourcesAndDest": [
            "run.sh",
            "/run.sh"
          ]
        },
        {
          "CmdLine": [
            "/run.sh"
          ],
          "Name": "cmd",
          "PrependShell": false
        }
      ]
    }
  ]
}