{
  "MetaArgs": null,
  "Stages": [
    {
      "Name": "",
      "BaseName": "markusma/nginx:1.7",
      "SourceCode": "FROM markusma/nginx:1.7",
      "Platform": "",
      "From": {
        "Image": "markusma/nginx:1.7"
      },
      "Commands": [
        {
          "Maintainer": "Markus Mattinen \u003cmarkus@gamma.fi\u003e",
          "Name": "maintainer"
        },
        {
          "Chown": "",
          "Name": "add",
          "SourcesAndDest": [
            "config/etc/supervisor/conf.d",
            "/etc/supervisor/conf.d"
          ]
        },
        {
          "Chown": "",
          "Name": "add",
          "SourcesAndDest": [
            "config/register",
            "/register"
          ]
        }
      ]
    }
  ]
}